MANIFEST.in
README.md
VERSION
pyproject.toml
setup.py
ckms/__init__.py
ckms/package.json
ckms/utils.py
ckms.egg-info/PKG-INFO
ckms.egg-info/SOURCES.txt
ckms.egg-info/dependency_links.txt
ckms.egg-info/entry_points.txt
ckms.egg-info/requires.txt
ckms.egg-info/top_level.txt
ckms/core/__init__.py
ckms/core/const.py
ckms/core/keychain.py
ckms/core/keyinspector.py
ckms/core/random.py
ckms/core/runlevel.py
ckms/core/exceptions/__init__.py
ckms/core/exceptions/malformed.py
ckms/core/local/__init__.py
ckms/core/local/models.py
ckms/core/local/types/__init__.py
ckms/core/local/types/contentencryptionkey.py
ckms/core/local/types/edwardscurvekeyspecification.py
ckms/core/local/types/ellipticcurvekeyspecification.py
ckms/core/local/types/hmac.py
ckms/core/local/types/key.py
ckms/core/local/types/localkey.py
ckms/core/local/types/localkeyspecification.py
ckms/core/local/types/parameterlesskey.py
ckms/core/local/types/rsakeyspecification.py
ckms/core/local/types/symmetrickeyspecification.py
ckms/core/local/types/transientkey.py
ckms/core/models/__init__.py
ckms/core/models/basekeyspecification.py
ckms/core/models/certificate.py
ckms/core/models/contentencryptionkey.py
ckms/core/models/joseheader_.py
ckms/core/models/joseobject.py
ckms/core/models/jsonb64.py
ckms/core/models/jsonwebencryption.py
ckms/core/models/jsonwebencryption_.py
ckms/core/models/jsonwebencryptionbase.py
ckms/core/models/jsonwebencryptionflattened.py
ckms/core/models/jsonwebencryptionrecipient.py
ckms/core/models/jsonwebencryptionwithrecipients.py
ckms/core/models/jsonwebsignature.py
ckms/core/models/keyspecification.py
ckms/core/models/octetb64.py
ckms/core/models/publickeyspecification.py
ckms/core/models/recipient.py
ckms/core/models/remoteblobparams.py
ckms/core/models/signature.py
ckms/core/provider/__init__.py
ckms/core/provider/provider.py
ckms/core/provider/tests/__init__.py
ckms/core/provider/tests/asymmetricsigningtestcase.py
ckms/core/provider/tests/baseprovidertestcase.py
ckms/core/provider/tests/encryptiontestcase.py
ckms/core/provider/tests/josebasetestcase.py
ckms/core/provider/tests/joseconsumertestcase.py
ckms/core/provider/tests/joseencryptiontestcase.py
